bitwarden_utils/__init__.py
bitwarden_utils/cli.py
bitwarden_utils/core/adapter.py
bitwarden_utils/core/history_recorder.py
bitwarden_utils/core/proc.py
bitwarden_utils/core/python_client.py
bitwarden_utils/core/session_retain.py
bitwarden_utils/core/models/item.py
bitwarden_utils/core/models/status.py
bitwarden_utils/core/utils/__init__.py
bitwarden_utils/core/utils/github_release.py
bw_utils-2.0.0.dist-info/LICENSE
bw_utils-2.0.0.dist-info/METADATA
bw_utils-2.0.0.dist-info/WHEEL
bw_utils-2.0.0.dist-info/entry_points.txt
bw_utils-2.0.0.dist-info/top_level.txt
bw_utils-2.0.0.dist-info/RECORD
