Metadata-Version: 2.1
Name: bw-utils
Version: 2.0.0
Summary: Bitwarden Utilities
Home-page: https://github.com/ZackaryW/bitwarden-utils
Author: ZackaryW
Classifier: Programming Language :: Python :: 3.11
Requires-Python: >=3.11
License-File: LICENSE
Requires-Dist: pydantic
Requires-Dist: click
